[{"id":null,"loginEmail":"john@wp.pl","password":"john","name":"John","city":"Gdynia","contactNumber":"111-111-111"},{"id":null,"loginEmail":"janek81@wp.pl","password":"Bc3e","name":"Jan","city":"Gdynia","contactNumber":"876543210"},{"id":null,"loginEmail":"anna92@gmail.com","password":"p9L$","name":"Anna","city":"Warszawa","contactNumber":"987654321"},{"id":null,"loginEmail":"marta1990@yahoo.com","password":"y9Efg","name":"Marta","city":"Gdańsk","contactNumber":"765432109"},{"id":null,"loginEmail":"adam123@wp.pl","password":"7eXg","name":"Adam","city":"Kraków","contactNumber":"654321098"},{"id":null,"loginEmail":"tomek77@gmail.com","password":"D8fR6#","name":"Tomek","city":"Łódź","contactNumber":"543210987"},{"id":null,"loginEmail":"ewa1988@onet.pl","password":"p3y$@k","name":"Ewa","city":"Wrocław","contactNumber":"432109876"},{"id":null,"loginEmail":"marek99@yahoo.com","password":"x!2A7g","name":"Marek","city":"Poznań","contactNumber":"321098765"},{"id":null,"loginEmail":"agata2002@gmail.com","password":"4s9T","name":"Agata","city":"Warszawa","contactNumber":"210987654"},{"id":null,"loginEmail":"lukasz80@wp.pl","password":"pZ5d!9","name":"Łukasz","city":"Gdynia","contactNumber":"109876543"},{"id":null,"loginEmail":"kinga1995@yahoo.com","password":"1@Fg","name":"Kinga","city":"Kraków","contactNumber":"098765432"},{"id":null,"loginEmail":"piotr123@onet.pl","password":"X7@q","name":"Piotr","city":"Warszawa","contactNumber":"987654321"},{"id":null,"loginEmail":"karolina89@gmail.com","password":"6gF*","name":"Karolina","city":"Gdańsk","contactNumber":"876543210"},{"id":null,"loginEmail":"michal77@wp.pl","password":"jP@6v","name":"Michał","city":"Poznań","contactNumber":"765432109"},{"id":null,"loginEmail":"anna2000@yahoo.com","password":"cR9z","name":"Anna","city":"Warszawa","contactNumber":"654321098"},{"id":null,"loginEmail":"tomasz1994@gmail.com","password":"5tQ*","name":"Tomasz","city":"Gdynia","contactNumber":"543210987"},{"id":null,"loginEmail":"kasia88@onet.pl","password":"2#v5","name":"Kasia","city":"Łódź","contactNumber":"432109876"},{"id":null,"loginEmail":"marcin1992@yahoo.com","password":"Fy4@p","name":"Marcin","city":"Warszawa","contactNumber":"321098765"},{"id":null,"loginEmail":"natalia2001@gmail.com","password":"b$8Qk","name":"Natalia","city":"Poznań","contactNumber":"210987654"},{"id":null,"loginEmail":"pawel85@wp.pl","password":"H9!n","name":"Paweł","city":"Warszawa","contactNumber":"109876543"},{"id":null,"loginEmail":"aleksandra93@yahoo.com","password":"G$z6j","name":"Aleksandra","city":"Kraków","contactNumber":"098765432"},{"id":null,"loginEmail":"jakub1988@gmail.com","password":"dY7*r","name":"Jakub","city":"Gdynia","contactNumber":"987654321"},{"id":null,"loginEmail":"anna1998@onet.pl","password":"9#yG","name":"Anna","city":"Warszawa","contactNumber":"876543210"},{"id":null,"loginEmail":"maciej2000@yahoo.com","password":"kT6*","name":"Maciej","city":"Wrocław","contactNumber":"765432109"},{"id":null,"loginEmail":"agnieszka92@gmail.com","password":"8@Rd6","name":"Agnieszka","city":"Gdańsk","contactNumber":"654321098"},{"id":null,"loginEmail":"pawel1995@wp.pl","password":"J6*m","name":"Paweł","city":"Warszawa","contactNumber":"543210987"},{"id":null,"loginEmail":"anna88@yahoo.com","password":"d@8V6","name":"Anna","city":"Poznań","contactNumber":"432109876"},{"id":null,"loginEmail":"tomasz1999@gmail.com","password":"4vE$","name":"Tomasz","city":"Warszawa","contactNumber":"321098765"},{"id":null,"loginEmail":"ewa2002@onet.pl","password":"M5#u","name":"Ewa","city":"Gdynia","contactNumber":"210987654"},{"id":null,"loginEmail":"michal91@yahoo.com","password":"9!kXb","name":"Michał","city":"Kraków","contactNumber":"109876543"},{"id":null,"loginEmail":"natalia1996@gmail.com","password":"W4*8","name":"Natalia","city":"Poznań","contactNumber":"098765432"},{"id":null,"loginEmail":"adam89@wp.pl","password":"U6$r","name":"Adam","city":"Warszawa","contactNumber":"987654321"},{"id":null,"loginEmail":"karolina2001@onet.pl","password":"7$Dn","name":"Karolina","city":"Gdańsk","contactNumber":"876543210"},{"id":null,"loginEmail":"marta87@yahoo.com","password":"R3*9m","name":"Marta","city":"Wrocław","contactNumber":"765432109"},{"id":null,"loginEmail":"piotr1999@gmail.com","password":"F#n6","name":"Piotr","city":"Gdynia","contactNumber":"654321098"},{"id":null,"loginEmail":"ola2003@wp.pl","password":"s2G@","name":"Ola","city":"Łódź","contactNumber":"543210987"},{"id":null,"loginEmail":"marcin88@yahoo.com","password":"H7%z","name":"Marcin","city":"Warszawa","contactNumber":"432109876"},{"id":null,"loginEmail":"iza1992@gmail.com","password":"d!3G","name":"Iza","city":"Poznań","contactNumber":"321098765"},{"id":null,"loginEmail":"adam90@onet.pl","password":"J5*7e","name":"Adam","city":"Warszawa","contactNumber":"210987654"},{"id":null,"loginEmail":"ania1990@yahoo.com","password":"gD#8","name":"Ania","city":"Kraków","contactNumber":"109876543"},{"id":null,"loginEmail":"tomek93@gmail.com","password":"6W!e","name":"Tomek","city":"Gdynia","contactNumber":"098765432"},{"id":null,"loginEmail":"monika87@wp.pl","password":"x7@D","name":"Monika","city":"Warszawa","contactNumber":"987654321"},{"id":null,"loginEmail":"michal2000@onet.pl","password":"p4!A","name":"Michał","city":"Gdańsk","contactNumber":"876543210"},{"id":null,"loginEmail":"agnieszka94@yahoo.com","password":"Y6@d","name":"Agnieszka","city":"Poznań","contactNumber":"765432109"},{"id":null,"loginEmail":"lukasz99@gmail.com","password":"a%3J","name":"Łukasz","city":"Warszawa","contactNumber":"654321098"},{"id":null,"loginEmail":"karolina92@wp.pl","password":"8$Gz","name":"Karolina","city":"Gdynia","contactNumber":"543210987"},{"id":null,"loginEmail":"jan01@wp.pl","password":"jan","name":"Jan","city":"Janowo","contactNumber":"123123123"},{"id":null,"loginEmail":"test@wp.pl","password":"test","name":"test@wp.pl","city":"test","contactNumber":"111111111"},{"id":null,"loginEmail":"aaa@wp.pl","password":"aaa","name":"aaa","city":"aaa","contactNumber":"111111111"},{"id":null,"loginEmail":"bbb@wp.pl","password":"bbb","name":"bbb","city":"bbb","contactNumber":"111111111"}]